snowcast/__init__.py
snowcast/data_wrangling/__init__.py
snowcast_Malachyiii-1.3.6.dist-info/LICENSE
snowcast_Malachyiii-1.3.6.dist-info/METADATA
snowcast_Malachyiii-1.3.6.dist-info/WHEEL
snowcast_Malachyiii-1.3.6.dist-info/top_level.txt
snowcast_Malachyiii-1.3.6.dist-info/RECORD
