Metadata-Version: 2.1
Name: snowcast-Malachyiii
Version: 1.3.6
Summary: A package for pulling down satellite imagery for snow forcasting
Home-page: https://github.com/Malachyiii/snowcast_package
Author: Malachy J. Moran III
Author-email: malachy.j.moran@gmail.com
License: UNKNOWN
Project-URL: Bug Tracker, https://github.com/Malachyiii/snowcast_package/issues
Platform: UNKNOWN
Classifier: Programming Language :: Python :: 3
Classifier: License :: OSI Approved :: MIT License
Classifier: Operating System :: OS Independent
Requires-Python: >=3.6
License-File: LICENSE
Requires-Dist: pandas
Requires-Dist: numpy (==1.21.0)
Requires-Dist: Rtree
Requires-Dist: geopandas
Requires-Dist: tornado (>=6.0)
Requires-Dist: dask[complete]
Requires-Dist: pystac-client
Requires-Dist: planetary-computer
Requires-Dist: rasterio
Requires-Dist: xarray-spatial
Requires-Dist: matplotlib
Requires-Dist: xarray
Requires-Dist: datashader
Requires-Dist: geotiff
Requires-Dist: geopy
Requires-Dist: shapely
Requires-Dist: imagecodecs
Requires-Dist: sklearn
Requires-Dist: requests
Requires-Dist: earthengine-api
Requires-Dist: httplib2 (==0.19.0)
Requires-Dist: rioxarray
Requires-Dist: seaborn
Requires-Dist: GDAL ; platform_system != "Windows"
